{"id":"ch5","voice":"Leda","duration":57.957,"words":[{"w":"The","s":0,"e":0.341},{"w":"family","s":0.341,"e":1.122},{"w":"found","s":1.122,"e":1.463},{"w":"her","s":1.463,"e":1.805},{"w":"just","s":1.805,"e":2.146},{"w":"after","s":2.146,"e":2.707},{"w":"dawn.","s":2.707,"e":3.634},{"w":"They","s":3.634,"e":3.976},{"w":"gathered","s":3.976,"e":4.756},{"w":"around","s":4.756,"e":5.317},{"w":"her","s":5.317,"e":5.659},{"w":"with","s":5.659,"e":6},{"w":"relief","s":6,"e":6.561},{"w":"and","s":6.561,"e":6.903},{"w":"love.","s":6.903,"e":7.829},{"w":"The","s":7.829,"e":8.171},{"w":"father","s":8.171,"e":8.732},{"w":"carried","s":8.732,"e":9.293},{"w":"her","s":9.293,"e":9.634},{"w":"back","s":9.634,"e":9.976},{"w":"to","s":9.976,"e":10.317},{"w":"the","s":10.317,"e":10.659},{"w":"house,","s":10.659,"e":11.244},{"w":"the","s":11.244,"e":11.586},{"w":"mother","s":11.586,"e":12.147},{"w":"wrapped","s":12.147,"e":12.708},{"w":"her","s":12.708,"e":13.049},{"w":"in","s":13.049,"e":13.39},{"w":"a","s":13.39,"e":13.732},{"w":"blanket,","s":13.732,"e":14.537},{"w":"and","s":14.537,"e":14.878},{"w":"the","s":14.878,"e":15.22},{"w":"youngest","s":15.22,"e":15.781},{"w":"girl","s":15.781,"e":16.122},{"w":"hugged","s":16.122,"e":16.683},{"w":"her","s":16.683,"e":17.025},{"w":"so","s":17.025,"e":17.366},{"w":"tightly","s":17.366,"e":17.927},{"w":"that","s":17.927,"e":18.269},{"w":"Lumo","s":18.269,"e":18.83},{"w":"let","s":18.83,"e":19.171},{"w":"out","s":19.171,"e":19.513},{"w":"a","s":19.513,"e":19.854},{"w":"tired","s":19.854,"e":20.415},{"w":"but","s":20.415,"e":20.756},{"w":"contented","s":20.756,"e":21.537},{"w":"sigh.","s":21.537,"e":22.464},{"w":"In","s":22.914,"e":23.259},{"w":"that","s":23.259,"e":23.604},{"w":"moment","s":23.604,"e":24.171},{"w":"she","s":24.171,"e":24.516},{"w":"understood","s":24.516,"e":25.305},{"w":"that","s":25.305,"e":25.65},{"w":"she","s":25.65,"e":25.995},{"w":"had","s":25.995,"e":26.34},{"w":"always","s":26.34,"e":26.907},{"w":"belonged.","s":26.907,"e":28.287},{"w":"She","s":28.287,"e":28.632},{"w":"did","s":28.632,"e":28.977},{"w":"not","s":28.977,"e":29.322},{"w":"need","s":29.322,"e":29.667},{"w":"boots","s":29.667,"e":30.012},{"w":"or","s":30.012,"e":30.357},{"w":"mittens","s":30.357,"e":30.924},{"w":"or","s":30.924,"e":31.269},{"w":"the","s":31.269,"e":31.614},{"w":"power","s":31.614,"e":32.181},{"w":"of","s":32.181,"e":32.526},{"w":"speech.","s":32.526,"e":33.462},{"w":"She","s":33.462,"e":33.807},{"w":"was","s":33.807,"e":34.153},{"w":"loved","s":34.153,"e":34.719},{"w":"for","s":34.719,"e":35.064},{"w":"exactly","s":35.064,"e":35.853},{"w":"what","s":35.853,"e":36.198},{"w":"she","s":36.198,"e":36.543},{"w":"was.","s":36.543,"e":37.48},{"w":"In","s":37.93,"e":38.273},{"w":"the","s":38.273,"e":38.615},{"w":"days","s":38.615,"e":38.958},{"w":"that","s":38.958,"e":39.301},{"w":"followed,","s":39.301,"e":40.329},{"w":"the","s":40.329,"e":40.672},{"w":"family","s":40.672,"e":41.455},{"w":"fed","s":41.455,"e":41.798},{"w":"her","s":41.798,"e":42.141},{"w":"warm","s":42.141,"e":42.484},{"w":"broth","s":42.484,"e":42.826},{"w":"and","s":42.826,"e":43.169},{"w":"little","s":43.169,"e":43.512},{"w":"pieces","s":43.512,"e":44.075},{"w":"of","s":44.075,"e":44.418},{"w":"cooked","s":44.418,"e":44.981},{"w":"meat.","s":44.981,"e":45.911},{"w":"She","s":45.911,"e":46.254},{"w":"rested","s":46.254,"e":46.817},{"w":"by","s":46.817,"e":47.16},{"w":"the","s":47.16,"e":47.502},{"w":"fire","s":47.502,"e":47.845},{"w":"and","s":47.845,"e":48.188},{"w":"watched","s":48.188,"e":48.751},{"w":"the","s":48.751,"e":49.094},{"w":"windows","s":49.094,"e":49.657},{"w":"frost","s":49.657,"e":50},{"w":"with","s":50,"e":50.342},{"w":"delicate","s":50.342,"e":51.126},{"w":"snowflake","s":51.126,"e":51.689},{"w":"patterns.","s":51.689,"e":52.84},{"w":"She","s":52.84,"e":53.182},{"w":"no","s":53.182,"e":53.525},{"w":"longer","s":53.525,"e":54.088},{"w":"felt","s":54.088,"e":54.431},{"w":"the","s":54.431,"e":54.774},{"w":"desire","s":54.774,"e":55.337},{"w":"to","s":55.337,"e":55.68},{"w":"become","s":55.68,"e":56.243},{"w":"something","s":56.243,"e":57.026},{"w":"else.","s":57.026,"e":57.957}]}